include/clipper/clipper-phs.h
include/clipper/cif_data_io.h
include/clipper/clipper-mmdbold.h
include/clipper/clipper-ccp4.h
include/clipper/clipper-minimol.h
include/clipper/clipper-cctbx.h
include/clipper/clipper-cif.h
include/clipper/clipper_cctbx.h
include/clipper/minimal-clipper-hkl.h
include/clipper/phs_io.h
include/clipper/minimal-clipper-map.h
include/clipper/clipper-cns.h
include/clipper/clipper-mmdb.h
include/clipper/clipper.h
include/clipper/clipper-contrib.h
include/clipper/mmdb/clipper_mmdb.h
include/clipper/cns/clipper-cns.h
include/clipper/cns/cns_map_io.h
include/clipper/cns/cns_hkl_io.h
include/clipper/minimol/minimol.h
include/clipper/minimol/minimol_io.h
include/clipper/minimol/container_minimol.h
include/clipper/minimol/clipper-minimol.h
include/clipper/minimol/minimol_utils.h
include/clipper/minimol/minimol_data.h
include/clipper/minimol/minimol_seq.h
include/clipper/contrib/skeleton.h
include/clipper/contrib/sfcalc.h
include/clipper/contrib/test_contrib.h
include/clipper/contrib/sfweight.h
include/clipper/contrib/mapfilter.h
include/clipper/contrib/originmatch.h
include/clipper/contrib/sfcalc_obs.h
include/clipper/contrib/edcalc.h
include/clipper/contrib/fffear.h
include/clipper/contrib/convolution_search.h
include/clipper/contrib/sfscale.h
include/clipper/contrib/clipper-contrib.h
include/clipper/contrib/function_object_bases.h
include/clipper/cif/cif_data_io.h
include/clipper/phs/phs_io.h
include/clipper/core/ramachandran.h
include/clipper/core/clipper_types.h
include/clipper/core/clipper_precision.h
include/clipper/core/nxmap_operator.h
include/clipper/core/hkl_datatypes.h
include/clipper/core/resol_basisfn.h
include/clipper/core/hkl_data.h
include/clipper/core/fftmap.h
include/clipper/core/spacegroup_data.h
include/clipper/core/hkl_compute.h
include/clipper/core/clipper_thread.h
include/clipper/core/xmap.h
include/clipper/core/derivs.h
include/clipper/core/clipper_memory.h
pysails-0.3.1.dist-info/top_level.txt
pysails-0.3.1.dist-info/RECORD
pysails-0.3.1.dist-info/entry_points.txt
pysails-0.3.1.dist-info/METADATA
pysails-0.3.1.dist-info/WHEEL
