Metadata-Version: 2.1
Name: pysails
Version: 0.3.1
Summary: Sails: Software for the Automated Identification of Linked Sugars
Author-email: Jordan Dialpuri <jordan.dialpuri@york.ac.uk>
Project-URL: Homepage, https://github.com/Dialpuri/Sails
Classifier: License :: OSI Approved :: BSD License
Requires-Python: >=3.10
Requires-Dist: tqdm
Requires-Dist: gemmi
Requires-Dist: numpy<2.0.0
Requires-Dist: typing-extensions
